{
    "getret": 0,
    "getmsg": "",
    "list":[
        {
            "username":"张三",
            "list":[
                {
                    "id":"111",
                    "filename":"aaaa"
                },
                {
                    "id": "111",
                    "filename": "aaaa"
                }
            ]
        },
        {
            "username": "张三",
            "list": [
                {
                    "id": "111",
                    "filename": "aaaa"
                },
                {
                    "id": "111",
                    "filename": "aaaa"
                }
            ]
        }
    ]
}